{
  "generatedAt": "2026-04-10T03:38:48.253Z",
  "assemblyId": "rebuilt-runtime",
  "sourceOfTruth": "config/runtime/assemblies.json",
  "runtimeInputRoot": ".runtime-deps/cursor/2.6/app",
  "outputRoot": "recovered/rebuilt/runtime-app",
  "topLevelOrigins": [
    {
      "path": "bin",
      "existsInRuntime": true,
      "source": "generated-runtime-asset",
      "contributors": [
        "external-runtime-input",
        "generated-runtime-asset"
      ]
    },
    {
      "path": "extensions",
      "existsInRuntime": true,
      "source": "rebuilt-override",
      "contributors": [
        "external-runtime-input",
        "rebuilt-override"
      ]
    },
    {
      "path": "node_modules",
      "existsInRuntime": true,
      "source": "external-runtime-input",
      "contributors": [
        "external-runtime-input"
      ]
    },
    {
      "path": "out",
      "existsInRuntime": true,
      "source": "rebuilt-override",
      "contributors": [
        "external-runtime-input",
        "phase2-overlay",
        "rebuilt-override"
      ]
    },
    {
      "path": "product.json",
      "existsInRuntime": true,
      "source": "generated-runtime-asset",
      "contributors": [
        "external-runtime-input",
        "generated-runtime-asset",
        "generated-runtime-asset"
      ]
    },
    {
      "path": "resources",
      "existsInRuntime": true,
      "source": "generated-runtime-asset",
      "contributors": [
        "external-runtime-input",
        "generated-runtime-asset"
      ]
    },
    {
      "path": "LICENSE.txt",
      "existsInRuntime": true,
      "source": "external-runtime-input",
      "contributors": [
        "external-runtime-input"
      ]
    },
    {
      "path": "ThirdPartyNotices.txt",
      "existsInRuntime": true,
      "source": "external-runtime-input",
      "contributors": [
        "external-runtime-input"
      ]
    }
  ],
  "meta": [
    {
      "path": "package.json",
      "source": "generated-report"
    },
    {
      "path": "mapped/runtime-origin-report.json",
      "source": "generated-report"
    }
  ],
  "passed": true
}
